blurple/__init__.py
blurple/ext/__init__.py
blurple/ext/help.py
blurple/ext/router.py
blurple/ext/time.py
blurple/io/__init__.py
blurple/io/message.py
blurple/io/reaction.py
blurple/io/reply.py
blurple/ui/__init__.py
blurple/ui/alert.py
blurple/ui/base.py
blurple/ui/style.py
blurple/ui/toast.py
blurple-1.0.3.dist-info/LICENSE
blurple-1.0.3.dist-info/METADATA
blurple-1.0.3.dist-info/WHEEL
blurple-1.0.3.dist-info/top_level.txt
blurple-1.0.3.dist-info/RECORD
