Metadata-Version: 2.1
Name: blurple
Version: 1.0.3
Summary: A front-end framework for discord.py
Home-page: https://github.com/cerusabi/blurple.py
Author: cerusabi
License: MIT
Project-URL: Issues, https://github.com/cerusabi/blurple.py/issues
Project-URL: Docs, https://lepto.tech/blurple.py
Classifier: Programming Language :: Python :: 3
Classifier: License :: OSI Approved :: MIT License
Classifier: Operating System :: OS Independent
Classifier: Intended Audience :: Developers
Classifier: Natural Language :: English
Classifier: Topic :: Software Development :: Libraries
Classifier: Topic :: Software Development :: Libraries :: Python Modules
Classifier: Topic :: Utilities
License-File: LICENSE
Requires-Dist: discord.py
Requires-Dist: python-dateutil
